proprietary/__init__.py
proprietary/__main__.py
proprietary/tests/__init__.py
proprietary/tests/test_1984.py
proprietary-0.1.0.dist-info/LICENSE.txt
proprietary-0.1.0.dist-info/METADATA
proprietary-0.1.0.dist-info/WHEEL
proprietary-0.1.0.dist-info/top_level.txt
proprietary-0.1.0.dist-info/RECORD
