Metadata-Version: 2.1
Name: proprietary
Version: 0.1.0
Summary: proprietary
Author-email: Johannes <johannes-programming@mailfence.com>
License: The MIT License (MIT)
Project-URL: Documentation, https://pypi.org/project/proprietary
Project-URL: Download, https://pypi.org/project/proprietary/#files
Project-URL: Source, https://github.com/johannes-programming/proprietary
Classifier: Development Status :: 2 - Pre-Alpha
Classifier: License :: OSI Approved :: MIT License
Classifier: Programming Language :: Python
Classifier: Programming Language :: Python :: 3
Classifier: Programming Language :: Python :: 3 :: Only
Requires-Python: >=3.8
License-File: LICENSE.txt
